Workbook

Sheet Read Me
A1: Smashed TV: speeding up the crops
A3: Plants grow faster when they are watered and fertilised, on top of the boost from every wave you clear.
A4: This workbook holds the numbers and works out grow times and profit for every strain.
A6: HOW TO USE
A7: Yellow cells with blue text are the numbers to tweak. Everything else is worked out from them.
A8: Water: how fast a plant grows watered, dry or wilted.
A9: Fertiliser: price and boosts for each bag.
A10: Strains: each strain's sell price, grow time, buds and potency.
A11: Grow Calculator: grow time and profit per plant for each strain, with each kind of care.
A12: Breeding: which two seeds make which, and what they cost to get.
A13: Upgrades: the later upgrades (prices still to decide).
A14: All numbers are a first go from the farm plan (FARM.md in the game's files), not final.

Sheet Water
A1: Water
A3: State | B3: Grow speed | C3: Buds lost | D3: How it happens
A4: Watered | B4: 1 | C4: 0 | D4: Water it at the tank with the watering can (or the sprinkler in stage 2). Dark soil and a drop icon show it.
A5: Dry | B5: 0.5 | C5: 0 | D5: Some time after watering it dries out and droops.
A6: Wilted | B6: 0.5 | C6: 1 | D6: Left dry too long: it loses a bud.
A8: Minutes a watering lasts | B8: 3

Sheet Fertiliser
A1: Fertiliser (one bag per plant, per harvest; bought at the shed)
A3: Fertiliser | B3: Price ($) | C3: Grows faster by | D3: Extra buds | E3: Extra potency
A4: None | B4: 0 | C4: 0 | D4: 0 | E4: 0
A5: Basic | B5: 10 | C5: 0.25 | D5: 0 | E5: 0
A6: Premium | B6: 30 | C6: 0.5 | D6: 1 | E6: 0
A7: Super Grow | B7: 80 | C7: 1 | D7: 1 | E7: 1
A9: Each extra potency point adds this much to the sell price: | E9: 0.15

Sheet Strains
A1: Strains
A3: Strain | B3: Type | C3: Tier | D3: Potency (/10) | E3: Sells for ($ a plant) | F3: Grows in (min, on its own) | G3: Or waves cleared | H3: Buds per plant | I3: Effect
A4: Northern Lights | B4: Indica | C4: Common | D4: 4 | E4: 40 | F4: 4 | G4: 2 | H4: 3 | I4: Heals 2 health
A5: Sour Diesel | B5: Sativa | C5: Uncommon | D5: 6 | E5: 75 | F5: 6 | G5: 3 | H5: 3 | I5: +25% run speed, +25% fire rate
A6: Granddaddy Purple | B6: Indica | C6: Uncommon | D6: 6 | E6: 80 | F6: 6 | G6: 3 | H6: 4 | I6: 40% less damage, 15% slower
A7: Blue Dream | B7: Hybrid | C7: Rare | D7: 7 | E7: 140 | F7: 9 | G7: 4 | H7: 3 | I7: Enemies at 70% speed
A8: Acapulco Gold | B8: Sativa | C8: Rare | D8: 7 | E8: 150 | F8: 10 | G8: 4 | H8: 2 | I8: Double cash from kills
A9: White Widow | B9: Hybrid | C9: Legendary | D9: 9 | E9: 300 | F9: 15 | G9: 6 | H9: 2 | I9: +60% damage, trippy screen

Sheet Grow Calculator
A1: Grow Calculator: one plant, watered unless it says dry
A3: GROW TIME (minutes, on its own, before the wave boost)
A4: Strain | B4: Dry, no fertiliser | C4: Watered, no fertiliser | D4: Watered + Basic | E4: Watered + Premium | F4: Watered + Super Grow
A5: =Strains!A4 -> Northern Lights | B5: =Strains!F4/(Water!$B$5*(1+Fertiliser!$C$4)) -> 8 | C5: =Strains!F4/(Water!$B$4*(1+Fertiliser!$C$4)) -> 4 | D5: =Strains!F4/(Water!$B$4*(1+Fertiliser!$C$5)) -> 3.2 | E5: =Strains!F4/(Water!$B$4*(1+Fertiliser!$C$6)) -> 2.6666667 | F5: =Strains!F4/(Water!$B$4*(1+Fertiliser!$C$7)) -> 2
A6: =Strains!A5 -> Sour Diesel | B6: =Strains!F5/(Water!$B$5*(1+Fertiliser!$C$4)) -> 12 | C6: =Strains!F5/(Water!$B$4*(1+Fertiliser!$C$4)) -> 6 | D6: =Strains!F5/(Water!$B$4*(1+Fertiliser!$C$5)) -> 4.8 | E6: =Strains!F5/(Water!$B$4*(1+Fertiliser!$C$6)) -> 4 | F6: =Strains!F5/(Water!$B$4*(1+Fertiliser!$C$7)) -> 3
A7: =Strains!A6 -> Granddaddy Purple | B7: =Strains!F6/(Water!$B$5*(1+Fertiliser!$C$4)) -> 12 | C7: =Strains!F6/(Water!$B$4*(1+Fertiliser!$C$4)) -> 6 | D7: =Strains!F6/(Water!$B$4*(1+Fertiliser!$C$5)) -> 4.8 | E7: =Strains!F6/(Water!$B$4*(1+Fertiliser!$C$6)) -> 4 | F7: =Strains!F6/(Water!$B$4*(1+Fertiliser!$C$7)) -> 3
A8: =Strains!A7 -> Blue Dream | B8: =Strains!F7/(Water!$B$5*(1+Fertiliser!$C$4)) -> 18 | C8: =Strains!F7/(Water!$B$4*(1+Fertiliser!$C$4)) -> 9 | D8: =Strains!F7/(Water!$B$4*(1+Fertiliser!$C$5)) -> 7.2 | E8: =Strains!F7/(Water!$B$4*(1+Fertiliser!$C$6)) -> 6 | F8: =Strains!F7/(Water!$B$4*(1+Fertiliser!$C$7)) -> 4.5
A9: =Strains!A8 -> Acapulco Gold | B9: =Strains!F8/(Water!$B$5*(1+Fertiliser!$C$4)) -> 20 | C9: =Strains!F8/(Water!$B$4*(1+Fertiliser!$C$4)) -> 10 | D9: =Strains!F8/(Water!$B$4*(1+Fertiliser!$C$5)) -> 8 | E9: =Strains!F8/(Water!$B$4*(1+Fertiliser!$C$6)) -> 6.6666667 | F9: =Strains!F8/(Water!$B$4*(1+Fertiliser!$C$7)) -> 5
A10: =Strains!A9 -> White Widow | B10: =Strains!F9/(Water!$B$5*(1+Fertiliser!$C$4)) -> 30 | C10: =Strains!F9/(Water!$B$4*(1+Fertiliser!$C$4)) -> 15 | D10: =Strains!F9/(Water!$B$4*(1+Fertiliser!$C$5)) -> 12 | E10: =Strains!F9/(Water!$B$4*(1+Fertiliser!$C$6)) -> 10 | F10: =Strains!F9/(Water!$B$4*(1+Fertiliser!$C$7)) -> 7.5
A12: PROFIT PER PLANT ($, sell price after fertiliser buds and potency, minus the bag)
A13: Strain | B13: Dry, no fertiliser | C13: Watered, no fertiliser | D13: Watered + Basic | E13: Watered + Premium | F13: Watered + Super Grow
A14: =Strains!A4 -> Northern Lights | B14: =Strains!E4*(Strains!H4+Fertiliser!$D$4)/Strains!H4*(1+Fertiliser!$E$4*Fertiliser!$E$9)-Fertiliser!$B$4 -> 40 | C14: =Strains!E4*(Strains!H4+Fertiliser!$D$4)/Strains!H4*(1+Fertiliser!$E$4*Fertiliser!$E$9)-Fertiliser!$B$4 -> 40 | D14: =Strains!E4*(Strains!H4+Fertiliser!$D$5)/Strains!H4*(1+Fertiliser!$E$5*Fertiliser!$E$9)-Fertiliser!$B$5 -> 30 | E14: =Strains!E4*(Strains!H4+Fertiliser!$D$6)/Strains!H4*(1+Fertiliser!$E$6*Fertiliser!$E$9)-Fertiliser!$B$6 -> 23.333333 | F14: =Strains!E4*(Strains!H4+Fertiliser!$D$7)/Strains!H4*(1+Fertiliser!$E$7*Fertiliser!$E$9)-Fertiliser!$B$7 -> -18.666667
A15: =Strains!A5 -> Sour Diesel | B15: =Strains!E5*(Strains!H5+Fertiliser!$D$4)/Strains!H5*(1+Fertiliser!$E$4*Fertiliser!$E$9)-Fertiliser!$B$4 -> 75 | C15: =Strains!E5*(Strains!H5+Fertiliser!$D$4)/Strains!H5*(1+Fertiliser!$E$4*Fertiliser!$E$9)-Fertiliser!$B$4 -> 75 | D15: =Strains!E5*(Strains!H5+Fertiliser!$D$5)/Strains!H5*(1+Fertiliser!$E$5*Fertiliser!$E$9)-Fertiliser!$B$5 -> 65 | E15: =Strains!E5*(Strains!H5+Fertiliser!$D$6)/Strains!H5*(1+Fertiliser!$E$6*Fertiliser!$E$9)-Fertiliser!$B$6 -> 70 | F15: =Strains!E5*(Strains!H5+Fertiliser!$D$7)/Strains!H5*(1+Fertiliser!$E$7*Fertiliser!$E$9)-Fertiliser!$B$7 -> 35
A16: =Strains!A6 -> Granddaddy Purple | B16: =Strains!E6*(Strains!H6+Fertiliser!$D$4)/Strains!H6*(1+Fertiliser!$E$4*Fertiliser!$E$9)-Fertiliser!$B$4 -> 80 | C16: =Strains!E6*(Strains!H6+Fertiliser!$D$4)/Strains!H6*(1+Fertiliser!$E$4*Fertiliser!$E$9)-Fertiliser!$B$4 -> 80 | D16: =Strains!E6*(Strains!H6+Fertiliser!$D$5)/Strains!H6*(1+Fertiliser!$E$5*Fertiliser!$E$9)-Fertiliser!$B$5 -> 70 | E16: =Strains!E6*(Strains!H6+Fertiliser!$D$6)/Strains!H6*(1+Fertiliser!$E$6*Fertiliser!$E$9)-Fertiliser!$B$6 -> 70 | F16: =Strains!E6*(Strains!H6+Fertiliser!$D$7)/Strains!H6*(1+Fertiliser!$E$7*Fertiliser!$E$9)-Fertiliser!$B$7 -> 35
A17: =Strains!A7 -> Blue Dream | B17: =Strains!E7*(Strains!H7+Fertiliser!$D$4)/Strains!H7*(1+Fertiliser!$E$4*Fertiliser!$E$9)-Fertiliser!$B$4 -> 140 | C17: =Strains!E7*(Strains!H7+Fertiliser!$D$4)/Strains!H7*(1+Fertiliser!$E$4*Fertiliser!$E$9)-Fertiliser!$B$4 -> 140 | D17: =Strains!E7*(Strains!H7+Fertiliser!$D$5)/Strains!H7*(1+Fertiliser!$E$5*Fertiliser!$E$9)-Fertiliser!$B$5 -> 130 | E17: =Strains!E7*(Strains!H7+Fertiliser!$D$6)/Strains!H7*(1+Fertiliser!$E$6*Fertiliser!$E$9)-Fertiliser!$B$6 -> 156.66667 | F17: =Strains!E7*(Strains!H7+Fertiliser!$D$7)/Strains!H7*(1+Fertiliser!$E$7*Fertiliser!$E$9)-Fertiliser!$B$7 -> 134.66667
A18: =Strains!A8 -> Acapulco Gold | B18: =Strains!E8*(Strains!H8+Fertiliser!$D$4)/Strains!H8*(1+Fertiliser!$E$4*Fertiliser!$E$9)-Fertiliser!$B$4 -> 150 | C18: =Strains!E8*(Strains!H8+Fertiliser!$D$4)/Strains!H8*(1+Fertiliser!$E$4*Fertiliser!$E$9)-Fertiliser!$B$4 -> 150 | D18: =Strains!E8*(Strains!H8+Fertiliser!$D$5)/Strains!H8*(1+Fertiliser!$E$5*Fertiliser!$E$9)-Fertiliser!$B$5 -> 140 | E18: =Strains!E8*(Strains!H8+Fertiliser!$D$6)/Strains!H8*(1+Fertiliser!$E$6*Fertiliser!$E$9)-Fertiliser!$B$6 -> 195 | F18: =Strains!E8*(Strains!H8+Fertiliser!$D$7)/Strains!H8*(1+Fertiliser!$E$7*Fertiliser!$E$9)-Fertiliser!$B$7 -> 178.75
A19: =Strains!A9 -> White Widow | B19: =Strains!E9*(Strains!H9+Fertiliser!$D$4)/Strains!H9*(1+Fertiliser!$E$4*Fertiliser!$E$9)-Fertiliser!$B$4 -> 300 | C19: =Strains!E9*(Strains!H9+Fertiliser!$D$4)/Strains!H9*(1+Fertiliser!$E$4*Fertiliser!$E$9)-Fertiliser!$B$4 -> 300 | D19: =Strains!E9*(Strains!H9+Fertiliser!$D$5)/Strains!H9*(1+Fertiliser!$E$5*Fertiliser!$E$9)-Fertiliser!$B$5 -> 290 | E19: =Strains!E9*(Strains!H9+Fertiliser!$D$6)/Strains!H9*(1+Fertiliser!$E$6*Fertiliser!$E$9)-Fertiliser!$B$6 -> 420 | F19: =Strains!E9*(Strains!H9+Fertiliser!$D$7)/Strains!H9*(1+Fertiliser!$E$7*Fertiliser!$E$9)-Fertiliser!$B$7 -> 437.5
A21: PROFIT PER MINUTE OF GROWING ($)
A22: Strain | B22: Dry, no fertiliser | C22: Watered, no fertiliser | D22: Watered + Basic | E22: Watered + Premium | F22: Watered + Super Grow
A23: =A5 -> Northern Lights | B23: =IFERROR(B14/B5,0) -> 5 | C23: =IFERROR(C14/C5,0) -> 10 | D23: =IFERROR(D14/D5,0) -> 9.375 | E23: =IFERROR(E14/E5,0) -> 8.75 | F23: =IFERROR(F14/F5,0) -> -9.3333333
A24: =A6 -> Sour Diesel | B24: =IFERROR(B15/B6,0) -> 6.25 | C24: =IFERROR(C15/C6,0) -> 12.5 | D24: =IFERROR(D15/D6,0) -> 13.541667 | E24: =IFERROR(E15/E6,0) -> 17.5 | F24: =IFERROR(F15/F6,0) -> 11.666667
A25: =A7 -> Granddaddy Purple | B25: =IFERROR(B16/B7,0) -> 6.6666667 | C25: =IFERROR(C16/C7,0) -> 13.333333 | D25: =IFERROR(D16/D7,0) -> 14.583333 | E25: =IFERROR(E16/E7,0) -> 17.5 | F25: =IFERROR(F16/F7,0) -> 11.666667
A26: =A8 -> Blue Dream | B26: =IFERROR(B17/B8,0) -> 7.7777778 | C26: =IFERROR(C17/C8,0) -> 15.555556 | D26: =IFERROR(D17/D8,0) -> 18.055556 | E26: =IFERROR(E17/E8,0) -> 26.111111 | F26: =IFERROR(F17/F8,0) -> 29.925926
A27: =A9 -> Acapulco Gold | B27: =IFERROR(B18/B9,0) -> 7.5 | C27: =IFERROR(C18/C9,0) -> 15 | D27: =IFERROR(D18/D9,0) -> 17.5 | E27: =IFERROR(E18/E9,0) -> 29.25 | F27: =IFERROR(F18/F9,0) -> 35.75
A28: =A10 -> White Widow | B28: =IFERROR(B19/B10,0) -> 10 | C28: =IFERROR(C19/C10,0) -> 20 | D28: =IFERROR(D19/D10,0) -> 24.166667 | E28: =IFERROR(E19/E10,0) -> 42 | F28: =IFERROR(F19/F10,0) -> 58.333333
A30: Notes
A31: A dry plant still uses the "Dry" speed; a wilted one also loses a bud (not counted here).
A32: Every wave you clear adds on top: a strain grows in the "Or waves cleared" count on the Strains tab even without waiting.
A33: Extra potency adds to the sell price by the % on the Fertiliser tab (a first guess).

Sheet Breeding
A1: Breeding: cross two seeds at the breeding table in the grow house
A2: Two seeds of one tier make one seed of the next tier. Which two you cross decides what you get.
A4: SETTINGS
A5: Waves until the new seed is ready | B5: 1
A6: Lucky chance (jumps a tier, or a special frosty seed) | B6: 0.05
A7: Frosty seeds sell for this much more | B7: 0.5
A9: SEEDS YOU CAN BUY (at the shed)
A10: Seed | B10: Price ($)
A11: Northern Lights | B11: 10
A12: Sour Diesel | B12: 30
A14: RECIPES
A15: Parent seed 1 | B15: Parent seed 2 | C15: Makes | D15: Tier | E15: Why | F15: Seeds bought to make one ($) | G15: Sells for ($ a plant)
A16: Northern Lights | B16: Northern Lights | C16: Granddaddy Purple | D16: =Strains!C6 -> Uncommon | E16: Indica + indica stays indica | F16: =2*B11 -> 20 | G16: =Strains!E6 -> 80
A17: Sour Diesel | B17: Sour Diesel | C17: Acapulco Gold | D17: =Strains!C8 -> Rare | E17: Sativa + sativa stays sativa | F17: =2*B12 -> 60 | G17: =Strains!E8 -> 150
A18: Granddaddy Purple | B18: Sour Diesel | C18: Blue Dream | D18: =Strains!C7 -> Rare | E18: Indica + sativa makes a hybrid | F18: =F16+B12 -> 50 | G18: =Strains!E7 -> 140
A19: Blue Dream | B19: Acapulco Gold | C19: White Widow | D19: =Strains!C9 -> Legendary | E19: The two rares make the legendary | F19: =F18+F17 -> 110 | G19: =Strains!E9 -> 300
A21: HOW MANY NORTHERN LIGHTS SEEDS A STRAIN TAKES (going the long way, all from the cheapest seed)
A22: Strain | B22: Northern Lights seeds
A23: Northern Lights | B23: 1
A24: Granddaddy Purple | B24: =2*B23 -> 2
A25: Rare (2 uncommons) | B25: =2*B24 -> 4
A26: White Widow (2 rares) | B26: =2*B25 -> 8
A28: Notes
A29: The "Seeds bought" column adds up what the parents cost at the shed; crossed seeds are free apart from their parents.
A30: A frosty seed grows the same strain, but sells for more by the % above.
A31: More recipes can be added later as new strains come in.

Sheet Upgrades
A1: Upgrades
A3: Upgrade | B3: Where | C3: What it does | D3: Price ($)
A4: Sprinkler | B4: Neighbour's block (stage 2) | C4: Waters the plots for you, so they never dry out.
A5: Grow lights | B5: Grow house (stage 2) | C5: Plants keep growing between waves.
A6: Compost bin | B6: Backyard | C6: Turns old plants into free Basic fertiliser.
A8: Prices not decided yet: fill them in.
